hope_smart_import/__init__.py
hope_smart_import/admin.py
hope_smart_import/apps.py
hope_smart_import/models.py
hope_smart_import/readers.py
hope_smart_import/shortcuts.py
hope_smart_import/types.pyi
hope_smart_import/migrations/0001_initial.py
hope_smart_import/migrations/__init__.py
hope_smart_import-0.5.1.dist-info/METADATA
hope_smart_import-0.5.1.dist-info/WHEEL
hope_smart_import-0.5.1.dist-info/top_level.txt
hope_smart_import-0.5.1.dist-info/RECORD
